CHANGELOG
LICENSE
MANIFEST.in
README.rst
setup.py
clipy/__init__.py
clipy/clipy_app.py
clipy/download.py
clipy/panel.py
clipy/request.py
clipy/ui.py
clipy/utils.py
clipy/video.py
clipy/window.py
clipy/youtube.py
clipy_dl.egg-info/PKG-INFO
clipy_dl.egg-info/SOURCES.txt
clipy_dl.egg-info/dependency_links.txt
clipy_dl.egg-info/entry_points.txt
clipy_dl.egg-info/requires.txt
clipy_dl.egg-info/top_level.txt