Metadata-Version: 1.1
Name: clipy-dl
Version: 0.9.7
Summary: YouTube video downloader
Home-page: https://github.com/stav/clipy
Author: Steven Almeroth
Author-email: sroth77@gmail.com
License: BSD
Download-URL: https://github.com/stav/clipy/archive/master.zip
Keywords: video downloader
Platform: UNKNOWN
Classifier: Development Status :: 3 - Alpha
Classifier: Environment :: Console
Classifier: Intended Audience :: End Users/Desktop
Classifier: License :: OSI Approved :: BSD License
Classifier: Programming Language :: Python :: 3
Classifier: Programming Language :: Python :: 3.4
Classifier: Topic :: Utilities
